xpay/__init__.py
xpay/api_requestor.py
xpay/api_version.py
xpay/app_info.py
xpay/error.py
xpay/http_client.py
xpay/multipart_data_generator.py
xpay/oauth.py
xpay/oauth_error.py
xpay/object_classes.py
xpay/py.typed
xpay/request_metrics.py
xpay/request_options.py
xpay/util.py
xpay/version.py
xpay/webhook.py
xpay/xpay_object.py
xpay/xpay_response.py
xpay/api_resources/__init__.py
xpay/api_resources/account.py
xpay/api_resources/account_link.py
xpay/api_resources/account_session.py
xpay/api_resources/apple_pay_domain.py
xpay/api_resources/application.py
xpay/api_resources/application_fee.py
xpay/api_resources/application_fee_refund.py
xpay/api_resources/balance.py
xpay/api_resources/balance_transaction.py
xpay/api_resources/bank_account.py
xpay/api_resources/capability.py
xpay/api_resources/card.py
xpay/api_resources/cash_balance.py
xpay/api_resources/charge.py
xpay/api_resources/connect_collection_transfer.py
xpay/api_resources/country_spec.py
xpay/api_resources/coupon.py
xpay/api_resources/credit_note.py
xpay/api_resources/credit_note_line_item.py
xpay/api_resources/customer.py
xpay/api_resources/customer_balance_transaction.py
xpay/api_resources/customer_cash_balance_transaction.py
xpay/api_resources/discount.py
xpay/api_resources/dispute.py
xpay/api_resources/ephemeral_key.py
xpay/api_resources/error_object.py
xpay/api_resources/event.py
xpay/api_resources/exchange_rate.py
xpay/api_resources/expandable_field.py
xpay/api_resources/file.py
xpay/api_resources/file_link.py
xpay/api_resources/funding_instructions.py
xpay/api_resources/invoice.py
xpay/api_resources/invoice_item.py
xpay/api_resources/invoice_line_item.py
xpay/api_resources/line_item.py
xpay/api_resources/list_object.py
xpay/api_resources/login_link.py
xpay/api_resources/mandate.py
xpay/api_resources/payment_intent.py
xpay/api_resources/payment_link.py
xpay/api_resources/payment_method.py
xpay/api_resources/payment_method_configuration.py
xpay/api_resources/payment_method_domain.py
xpay-7.4.0.dist-info/LICENSE
xpay-7.4.0.dist-info/METADATA
xpay-7.4.0.dist-info/WHEEL
xpay-7.4.0.dist-info/top_level.txt
xpay-7.4.0.dist-info/RECORD
