Metadata-Version: 2.1
Name: xpay
Version: 7.4.0
Summary: Python bindings for the XPay API
Home-page: https://github.com/xxxpay/xpay-python
Author: XPay
Author-email: support@xpay.com
License: MIT
Project-URL: Bug Tracker, https://github.com/xxxpay/xpay-python/issues
Project-URL: Changes, https://github.com/xxxpay/xpay-python/blob/master/CHANGELOG.md
Project-URL: Documentation, https://xpay.com/docs/api/?lang=python
Project-URL: Source Code, https://github.com/xxxpay/xpay-python
Keywords: xpay api payments
Classifier: Development Status :: 5 - Production/Stable
Classifier: Intended Audience :: Developers
Classifier: License :: OSI Approved :: MIT License
Classifier: Operating System :: OS Independent
Classifier: Programming Language :: Python
Classifier: Programming Language :: Python :: 3
Classifier: Programming Language :: Python :: 3 :: Only
Classifier: Programming Language :: Python :: 3.6
Classifier: Programming Language :: Python :: 3.7
Classifier: Programming Language :: Python :: 3.8
Classifier: Programming Language :: Python :: 3.9
Classifier: Programming Language :: Python :: 3.10
Classifier: Programming Language :: Python :: 3.11
Classifier: Programming Language :: Python :: 3.12
Classifier: Programming Language :: Python :: Implementation :: CPython
Classifier: Programming Language :: Python :: Implementation :: PyPy
Classifier: Topic :: Software Development :: Libraries :: Python Modules
Requires-Python: >=3.6
License-File: LICENSE
Requires-Dist: typing-extensions <=4.2.0,>3.7.2 ; python_version < "3.7"
Requires-Dist: requests >=2.20 ; python_version >= "3.0"
Requires-Dist: typing-extensions >=4.5.0 ; python_version >= "3.7"
